[
	{
		"name": "Density",
		"children": [
			{
				"name": "span",
				"content": "Content 1",
				"native": true
			},
			{
				"name": "span",
				"content": "Content 2",
				"native": true
			},
			{
				"name": "span",
				"content": "Content 3",
				"native": true
			}
		],
		"examples": [
			{
				"name": "Functional",
				"density": "functional",
				"props": {},
				"style": {
					"width": "200px"
				}
			},
			{
				"name": "(Default) Regular",
				"density": "regular",
				"props": {},
				"style": {
					"width": "200px"
				}
			},
			{
				"name": "Expressive",
				"density": "expressive",
				"props": {},
				"style": {
					"width": "200px"
				}
			}
		]
	},
	{
		"name": "Variant",
		"examples": [
			{
				"name": "(Default) Simple",
				"props": {},
				"style": {
					"width": "200px"
				},
				"children": [
					{
						"name": "span",
						"content": "Content 1",
						"native": true
					},
					{
						"name": "span",
						"content": "Content 2",
						"native": true
					},
					{
						"name": "span",
						"content": "Content 3",
						"native": true
					}
				]
			},
			{
				"name": "Divider",
				"props": {
					"variant": "divider"
				},
				"style": {
					"width": "200px"
				},
				"children": [
					{
						"name": "span",
						"content": "Content 1",
						"native": true
					},
					{
						"name": "divider",
						"content": ""
					},
					{
						"name": "span",
						"content": "Content 2",
						"native": true
					},
					{
						"name": "divider",
						"content": ""
					},
					{
						"name": "span",
						"content": "Content 3",
						"native": true
					}
				]
			}
		]
	},
	{
		"name": "Gap",
		"children": [
			{
				"name": "span",
				"content": "Content 1",
				"native": true
			},
			{
				"name": "span",
				"content": "Content 2",
				"native": true
			},
			{
				"name": "span",
				"content": "Content 3",
				"native": true
			}
		],
		"examples": [
			{
				"name": "none",
				"props": {
					"gap": "none"
				},
				"style": {
					"width": "200px"
				}
			},
			{
				"name": "3x-small",
				"props": {
					"gap": "3x-small"
				},
				"style": {
					"width": "200px"
				}
			},
			{
				"name": "2x-small",
				"props": {
					"gap": "2x-small"
				},
				"style": {
					"width": "200px"
				}
			},
			{
				"name": "x-small",
				"props": {
					"gap": "x-small"
				},
				"style": {
					"width": "200px"
				}
			},
			{
				"name": "(Default) small",
				"props": {
					"gap": "small"
				},
				"style": {
					"width": "200px"
				}
			},
			{
				"name": "medium",
				"props": {
					"gap": "medium"
				},
				"style": {
					"width": "200px"
				}
			},
			{
				"name": "large",
				"props": {
					"gap": "large"
				},
				"style": {
					"width": "200px"
				}
			},
			{
				"name": "x-large",
				"props": {
					"gap": "x-large"
				},
				"style": {
					"width": "200px"
				}
			},
			{
				"name": "2x-large",
				"props": {
					"gap": "2x-large"
				},
				"style": {
					"width": "200px"
				}
			},
			{
				"name": "3x-large",
				"props": {
					"gap": "3x-large"
				},
				"style": {
					"width": "200px"
				}
			}
		]
	},
	{
		"name": "Direction",
		"children": [
			{
				"name": "span",
				"content": "Content 1",
				"native": true
			},
			{
				"name": "span",
				"content": "Content 2",
				"native": true
			},
			{
				"name": "span",
				"content": "Content 3",
				"native": true
			}
		],
		"examples": [
			{
				"name": "(Default) Column",
				"props": {},
				"style": {
					"width": "200px"
				}
			},
			{
				"name": "Row",
				"style": {
					"height": "100px"
				},
				"props": {
					"direction": "row"
				}
			}
		]
	},
	{
		"name": "Wrap",
		"children": [
			{
				"name": "span",
				"content": "Content 1",
				"native": true
			},
			{
				"name": "span",
				"content": "Content 2",
				"native": true
			},
			{
				"name": "span",
				"content": "Content 3",
				"native": true
			}
		],
		"examples": [
			{
				"name": "(Default) No Wrap: Column",
				"style": {
					"width": "160px",
					"height": "88px"
				},
				"props": {}
			},
			{
				"name": "No Wrap: Row",
				"style": {
					"width": "160px",
					"height": "88px"
				},
				"props": {
					"direction": "row"
				}
			},
			{
				"name": "Wrap: Column",
				"style": {
					"width": "160px",
					"height": "120px"
				},
				"props": {
					"wrap": true
				}
			},
			{
				"name": "Wrap: Row",
				"style": {
					"width": "180px",
					"height": "100px"
				},
				"props": {
					"direction": "row",
					"wrap": true
				}
			}
		]
	},
	{
		"name": "Alignment Column",
		"children": [
			{
				"name": "span",
				"content": "Content 1",
				"native": true
			},
			{
				"name": "span",
				"content": "Content 2",
				"native": true
			},
			{
				"name": "span",
				"content": "Content 3",
				"native": true
			}
		],
		"examples": [
			{
				"name": "(Default) Stretch",
				"style": {
					"width": "200px"
				},
				"props": {
					"alignment": "stretch"
				}
			},
			{
				"name": "Start",
				"style": {
					"width": "200px"
				},
				"props": {
					"alignment": "start"
				}
			},
			{
				"name": "Center",
				"style": {
					"width": "200px"
				},
				"props": {
					"alignment": "center"
				}
			},
			{
				"name": "End",
				"style": {
					"width": "200px"
				},
				"props": {
					"alignment": "end"
				}
			}
		]
	},
	{
		"name": "Alignment Row",
		"children": [
			{
				"name": "span",
				"content": "Content 1",
				"native": true
			},
			{
				"name": "span",
				"content": "Content 2",
				"native": true
			},
			{
				"name": "span",
				"content": "Content 3",
				"native": true
			}
		],
		"examples": [
			{
				"name": "(Default) Stretch",
				"style": {
					"height": "100px"
				},
				"props": {
					"alignment": "stretch",
					"direction": "row"
				}
			},
			{
				"name": "Start",
				"style": {
					"height": "100px"
				},
				"props": {
					"alignment": "start",
					"direction": "row"
				}
			},
			{
				"name": "Center",
				"style": {
					"height": "100px"
				},
				"props": {
					"alignment": "center",
					"direction": "row"
				}
			},
			{
				"name": "End",
				"style": {
					"height": "100px"
				},
				"props": {
					"alignment": "end",
					"direction": "row"
				}
			}
		]
	},
	{
		"name": "Justify Content Column",
		"children": [
			{
				"name": "span",
				"content": "Content 1",
				"native": true
			},
			{
				"name": "span",
				"content": "Content 2",
				"native": true
			},
			{
				"name": "span",
				"content": "Content 3",
				"native": true
			}
		],
		"examples": [
			{
				"name": "(Default) Start",
				"style": {
					"width": "200px",
					"height": "200px"
				},
				"props": {
					"justifyContent": "start"
				}
			},
			{
				"name": "Center",
				"style": {
					"width": "200px",
					"height": "200px"
				},
				"props": {
					"justifyContent": "center"
				}
			},
			{
				"name": "End",
				"style": {
					"width": "200px",
					"height": "200px"
				},
				"props": {
					"justifyContent": "end"
				}
			},
			{
				"name": "Space-Between",
				"style": {
					"width": "200px",
					"height": "200px"
				},
				"props": {
					"justifyContent": "space-between"
				}
			}
		]
	},
	{
		"name": "Justify Content Row",
		"children": [
			{
				"name": "span",
				"content": "Content 1",
				"native": true
			},
			{
				"name": "span",
				"content": "Content 2",
				"native": true
			},
			{
				"name": "span",
				"content": "Content 3",
				"native": true
			}
		],
		"examples": [
			{
				"name": "(Default) Start",
				"style": {
					"width": "300px"
				},
				"props": {
					"justifyContent": "start",
					"direction": "row"
				}
			},
			{
				"name": "Center",
				"style": {
					"width": "300px"
				},
				"props": {
					"justifyContent": "center",
					"direction": "row"
				}
			},
			{
				"name": "End",
				"style": {
					"width": "300px"
				},
				"props": {
					"justifyContent": "end",
					"direction": "row"
				}
			},
			{
				"name": "Space-Between",
				"style": {
					"width": "300px"
				},
				"props": {
					"justifyContent": "space-between",
					"direction": "row"
				}
			}
		]
	}
]
