[
	{
		"name": "Density",
		"children": [
			{
				"name": "button"
			}
		],
		"examples": [
			{
				"name": "Functional",
				"className": "db-density-functional",
				"props": {
					"content": "Tooltip",
					"id": "tooltip-01"
				}
			},
			{
				"name": "(Default) Regular",
				"className": "db-density-regular",
				"props": {
					"content": "Tooltip",
					"id": "tooltip-02"
				}
			},
			{
				"name": "Expressive",
				"className": "db-density-expressive",
				"props": {
					"content": "Tooltip",
					"id": "tooltip-03"
				}
			}
		]
	},
	{
		"name": "Variant",
		"children": [
			{
				"name": "button"
			}
		],
		"examples": [
			{
				"name": "(Default) With arrow",
				"props": {
					"content": "Tooltip",
					"id": "tooltip-04"
				}
			},
			{
				"name": "Basic",
				"props": {
					"content": "Tooltip",
					"variant": "basic",
					"id": "tooltip-05"
				}
			}
		]
	},
	{
		"name": "Emphasis",
		"children": [
			{
				"name": "button"
			}
		],
		"examples": [
			{
				"name": "(Default) Weak",
				"props": {
					"content": "Tooltip",
					"id": "tooltip-06"
				}
			},
			{
				"name": "Strong",
				"props": {
					"content": "Tooltip",
					"emphasis": "strong",
					"id": "tooltip-07"
				}
			}
		]
	},
	{
		"name": "Placement",
		"children": [
			{
				"name": "button"
			}
		],
		"examples": [
			{
				"name": "bottom-start",
				"props": {
					"content": "Tooltip",
					"placement": "bottom-start",
					"id": "tooltip-08-start"
				}
			},
			{
				"name": "(Default) bottom",
				"props": {
					"content": "Tooltip",
					"placement": "bottom",
					"id": "tooltip-08"
				}
			},
			{
				"name": "bottom-end",
				"props": {
					"content": "Tooltip",
					"placement": "bottom-end",
					"id": "tooltip-08-end"
				}
			},
			{
				"name": "left-start",
				"props": {
					"content": "Tooltip",
					"placement": "left-start",
					"id": "tooltip-10-start"
				}
			},
			{
				"name": "left",
				"props": {
					"content": "Tooltip",
					"placement": "left",
					"id": "tooltip-10"
				}
			},
			{
				"name": "left-end",
				"props": {
					"content": "Tooltip",
					"placement": "left-end",
					"id": "tooltip-10-end"
				}
			},
			{
				"name": "right-start",
				"props": {
					"content": "Tooltip",
					"placement": "right-start",
					"id": "tooltip-11-start"
				}
			},
			{
				"name": "right",
				"props": {
					"content": "Tooltip",
					"placement": "right",
					"id": "tooltip-11"
				}
			},
			{
				"name": "right-end",
				"props": {
					"content": "Tooltip",
					"placement": "right-end",
					"id": "tooltip-11-end"
				}
			},
			{
				"name": "top-start",
				"props": {
					"content": "Tooltip",
					"placement": "top-start",
					"id": "tooltip-09-start"
				}
			},
			{
				"name": "top",
				"props": {
					"content": "Tooltip",
					"placement": "top",
					"id": "tooltip-09"
				}
			},
			{
				"name": "top-end",
				"props": {
					"content": "Tooltip",
					"placement": "top-end",
					"id": "tooltip-09-end"
				}
			}
		]
	},
	{
		"name": "Width",
		"children": [
			{
				"name": "button"
			}
		],
		"examples": [
			{
				"name": "(Default) Auto",
				"props": {
					"content": "Max width, lorem ipsum dolor sit amet, consetetur sadipscing",
					"id": "tooltip-12"
				}
			},
			{
				"name": "Fixed",
				"props": {
					"content": "Max width, lorem ipsum dolor sit amet, consetetur sadipscing",
					"width": "fixed",
					"id": "tooltip-13"
				}
			}
		]
	},
	{
		"name": "Animations",
		"children": [
			{
				"name": "button"
			}
		],
		"examples": [
			{
				"name": "(Default) Animation no delay",
				"props": {
					"content": "Tooltip",
					"id": "tooltip-14"
				}
			},
			{
				"name": "Delay slow",
				"props": {
					"content": "Tooltip",
					"delay": "slow",
					"id": "tooltip-15"
				}
			},
			{
				"name": "Delay fast",
				"props": {
					"content": "Tooltip",
					"delay": "fast",
					"id": "tooltip-16"
				}
			},
			{
				"name": "No animation",
				"props": {
					"content": "Tooltip",
					"animation": "disabled",
					"id": "tooltip-17"
				}
			}
		]
	}
]
